LICENSE
README.md
pyproject.toml
src/sb_async/async_helpers.py
src/sb_async/async_job.py
src/sb_async/async_queue.py
src/sb_async/async_threadpool.py
src/sb_async.egg-info/PKG-INFO
src/sb_async.egg-info/SOURCES.txt
src/sb_async.egg-info/dependency_links.txt
src/sb_async.egg-info/top_level.txt