Metadata-Version: 2.4
Name: sb-async
Version: 0.0.2
Summary: A high-performance async thread pool with process-based execution and forceful job termination
Author-email: Stephen Booth <stephen.booth.za@gmail.com>
Project-URL: homepage, https://github.com/sboothza/sb-async
Keywords: async,threadpool,multiprocessing,asyncio,parallel,concurrent
Classifier: Programming Language :: Python :: 3.12
Classifier: License :: OSI Approved :: MIT License
Classifier: Operating System :: OS Independent
Classifier: Development Status :: 5 - Production/Stable
Classifier: Intended Audience :: Developers
Classifier: Topic :: Software Development :: Libraries :: Python Modules
Classifier: Topic :: System :: Distributed Computing
Requires-Python: >=3.12
License-File: LICENSE
Dynamic: license-file
